LICENSE.txt
README.md
setup.py
mbil/__init__.py
mbil/dataset.py
mbil/mbilscore.py
mbil/mbilsearch.py
mbil/output.py
mbil/scores.py
mbil_py.egg-info/PKG-INFO
mbil_py.egg-info/SOURCES.txt
mbil_py.egg-info/dependency_links.txt
mbil_py.egg-info/top_level.txt